no_llm/__init__.py
no_llm/_base.py
no_llm/_utils.py
no_llm/cli.py
no_llm/errors.py
no_llm/presets.py
no_llm/py.typed
no_llm/registry.py
no_llm/settings.py
no_llm/embeddings/__init__.py
no_llm/integrations/__init__.py
no_llm/integrations/_utils.py
no_llm/integrations/pydantic_ai.py
no_llm/models/__init__.py
no_llm/models/registry.py
no_llm/models/config/__init__.py
no_llm/models/config/benchmarks.py
no_llm/models/config/enums.py
no_llm/models/config/errors.py
no_llm/models/config/integrations.py
no_llm/models/config/metadata.py
no_llm/models/config/model.py
no_llm/models/config/parameters.py
no_llm/models/config/properties.py
no_llm/models/model_configs/__init__.py
no_llm/models/model_configs/claude/__init__.py
no_llm/models/model_configs/claude/base.py
no_llm/models/model_configs/claude/claude_3_5_haiku.py
no_llm/models/model_configs/claude/claude_3_5_sonnet.py
no_llm/models/model_configs/claude/claude_3_5_sonnet_v2.py
no_llm/models/model_configs/claude/claude_3_7_sonnet.py
no_llm/models/model_configs/claude/claude_3_haiku.py
no_llm/models/model_configs/claude/claude_3_opus.py
no_llm/models/model_configs/claude/claude_3_sonnet.py
no_llm/models/model_configs/claude/claude_4_opus.py
no_llm/models/model_configs/claude/claude_4_sonnet.py
no_llm/models/model_configs/deepseek/__init__.py
no_llm/models/model_configs/deepseek/base.py
no_llm/models/model_configs/deepseek/deepseek_chat.py
no_llm/models/model_configs/deepseek/deepseek_r1_llama_70b_distilled.py
no_llm/models/model_configs/deepseek/deepseek_reasoner.py
no_llm/models/model_configs/gemini/__init__.py
no_llm/models/model_configs/gemini/base.py
no_llm/models/model_configs/gemini/gemini_1_5_flash.py
no_llm/models/model_configs/gemini/gemini_1_5_pro.py
no_llm/models/model_configs/gemini/gemini_2_0_flash.py
no_llm/models/model_configs/gemini/gemini_2_0_flash_lite.py
no_llm/models/model_configs/gemini/gemini_2_0_flash_thinking.py
no_llm/models/model_configs/gemini/gemini_2_0_pro.py
no_llm-0.1.14.dist-info/METADATA
no_llm-0.1.14.dist-info/WHEEL
no_llm-0.1.14.dist-info/licenses/LICENSE.txt
no_llm-0.1.14.dist-info/RECORD
