Metadata-Version: 2.4
Name: no_llm
Version: 0.1.14
Summary: Standard Interface for Large Language Models
Project-URL: Documentation, https://github.com/Noxus-AI/no-llm#readme
Project-URL: Issues, https://github.com/Noxus-AI/no-llm/issues
Project-URL: Source, https://github.com/Noxus-AI/no-llm
Author-email: pedro <pedro@noxus.ai>
License: MIT
License-File: LICENSE.txt
Classifier: Development Status :: 4 - Beta
Classifier: Programming Language :: Python
Classifier: Programming Language :: Python :: 3.8
Classifier: Programming Language :: Python :: 3.9
Classifier: Programming Language :: Python :: 3.10
Classifier: Programming Language :: Python :: 3.11
Classifier: Programming Language :: Python :: 3.12
Classifier: Programming Language :: Python :: Implementation :: CPython
Classifier: Programming Language :: Python :: Implementation :: PyPy
Requires-Python: >=3.10
Requires-Dist: loguru>=0.7.0
Requires-Dist: pydantic-ai>=0.2.0
Requires-Dist: pydantic>=2.0.0
Requires-Dist: pyyaml>=6.0.0
Requires-Dist: typing-extensions>=4.0.0
Provides-Extra: pydantic-ai
Requires-Dist: pydantic-ai>=0.2.0; extra == 'pydantic-ai'
